{
  "ASNS": {
    "Settlement Date": "Dec 13, 2024",
    "Short Interest": 211440,
    "Avg. Daily Volume": 5430000,
    "Short Float": 237530,
    "Short Ratio": "3.89%"
  },
  "ADD": {
    "Settlement Date": "Dec 13, 2024",
    "Short Interest": 151400,
    "Avg. Daily Volume": 580000,
    "Short Float": 191510,
    "Short Ratio": "26.10%"
  },
  "MULN": {
    "Settlement Date": "Dec 13, 2024",
    "Short Interest": 2350000,
    "Avg. Daily Volume": 8730000,
    "Short Float": 3280000,
    "Short Ratio": "26.92%"
  },
  "VRME": {
    "Settlement Date": "Dec 13, 2024",
    "Short Interest": 25490,
    "Avg. Daily Volume": 8170000,
    "Short Float": 77980,
    "Short Ratio": "0.31%"
  },
  "NXU": {
    "Settlement Date": "Dec 13, 2024",
    "Short Interest": 163380,
    "Avg. Daily Volume": 14220000,
    "Short Float": 6960000,
    "Short Ratio": "1.15%"
  },
  "GFAI": {
    "Settlement Date": "Dec 13, 2024",
    "Short Interest": 120880,
    "Avg. Daily Volume": 8359999.999999999,
    "Short Float": 605210,
    "Short Ratio": "1.45%"
  },
  "LPSN": {
    "Settlement Date": "Dec 13, 2024",
    "Short Interest": 7220000,
    "Avg. Daily Volume": 73240000,
    "Short Float": 1840000,
    "Short Ratio": "9.86%"
  },
  "FFIE": {
    "Settlement Date": "Dec 13, 2024",
    "Short Interest": 10980000,
    "Avg. Daily Volume": 40990000,
    "Short Float": 6800000,
    "Short Ratio": "26.80%"
  },
  "APM": {
    "Settlement Date": "Dec 13, 2024",
    "Short Interest": 11110,
    "Avg. Daily Volume": 2170000,
    "Short Float": 42660,
    "Short Ratio": "0.51%"
  },
  "BJDX": {
    "Settlement Date": "Dec 13, 2024",
    "Short Interest": 27100,
    "Avg. Daily Volume": 550000,
    "Short Float": 622100,
    "Short Ratio": "4.93%"
  },
  "HOLO": {
    "Settlement Date": "Dec 13, 2024",
    "Short Interest": 2760000,
    "Avg. Daily Volume": 20440000,
    "Short Float": 4099999.9999999995,
    "Short Ratio": "13.48%"
  },
  "GDHG": {
    "Settlement Date": "Dec 13, 2024",
    "Short Interest": 25220,
    "Avg. Daily Volume": 1970000,
    "Short Float": 274790,
    "Short Ratio": "1.28%"
  },
  "PERF": {
    "Settlement Date": "Dec 13, 2024",
    "Short Interest": 83010,
    "Avg. Daily Volume": 25730000,
    "Short Float": 62360,
    "Short Ratio": "0.32%"
  },
  "NVNI": {
    "Settlement Date": "Dec 13, 2024",
    "Short Interest": 17120,
    "Avg. Daily Volume": 8070000,
    "Short Float": 9150,
    "Short Ratio": "0.21%"
  },
  "WLDS": {
    "Settlement Date": "Dec 13, 2024",
    "Short Interest": 58060,
    "Avg. Daily Volume": 1970000,
    "Short Float": 596100,
    "Short Ratio": "2.95%"
  },
  "SIDU": {
    "Settlement Date": "Dec 13, 2024",
    "Short Interest": 534870,
    "Avg. Daily Volume": 8330000,
    "Short Float": 604110,
    "Short Ratio": "6.42%"
  },
  "MLGO": {
    "Settlement Date": "Dec 13, 2024",
    "Short Interest": 350660,
    "Avg. Daily Volume": 9740000,
    "Short Float": 1760000,
    "Short Ratio": "3.60%"
  },
  "BDMD": {
    "Settlement Date": "Dec 13, 2024",
    "Short Interest": 23740,
    "Avg. Daily Volume": "N/A",
    "Short Float": 45670,
    "Short Ratio": "N/A"
  },
  "REKR": {
    "Settlement Date": "Dec 13, 2024",
    "Short Interest": 14610000,
    "Avg. Daily Volume": 85770000,
    "Short Float": 933200,
    "Short Ratio": "17.04%"
  },
  "AMPG": {
    "Settlement Date": "Dec 13, 2024",
    "Short Interest": 2290000,
    "Avg. Daily Volume": 11860000,
    "Short Float": 5150000,
    "Short Ratio": "19.34%"
  },
  "NEHC": {
    "Settlement Date": "Dec 13, 2024",
    "Short Interest": 55350,
    "Avg. Daily Volume": 4820000,
    "Short Float": 59020,
    "Short Ratio": "1.15%"
  },
  "HOUR": {
    "Settlement Date": "Dec 13, 2024",
    "Short Interest": 28020,
    "Avg. Daily Volume": 1730000,
    "Short Float": 19910,
    "Short Ratio": "1.62%"
  },
  "ONCO": {
    "Settlement Date": "Dec 13, 2024",
    "Short Interest": 57340,
    "Avg. Daily Volume": 3500000,
    "Short Float": 750620,
    "Short Ratio": "1.64%"
  },
  "AISP": {
    "Settlement Date": "Dec 13, 2024",
    "Short Interest": 2430000,
    "Avg. Daily Volume": 14640000,
    "Short Float": 1110000,
    "Short Ratio": "16.62%"
  },
  "BMR": {
    "Settlement Date": "Dec 13, 2024",
    "Short Interest": 624300,
    "Avg. Daily Volume": 10760000,
    "Short Float": 200620,
    "Short Ratio": "5.80%"
  },
  "VSTM": {
    "Settlement Date": "Dec 13, 2024",
    "Short Interest": 2620000,
    "Avg. Daily Volume": 39640000,
    "Short Float": 989260,
    "Short Ratio": "6.61%"
  },
  "HKD": {
    "Settlement Date": "Dec 13, 2024",
    "Short Interest": 723470,
    "Avg. Daily Volume": 27300000,
    "Short Float": 1400000,
    "Short Ratio": "2.65%"
  }
}