{
  "MDAI": {
    "Settlement Date": "Nov 15, 2024",
    "Short Interest": 801100,
    "Avg. Daily Volume": 234360,
    "Short Float": "9.06%",
    "Short Ratio": "3.42"
  },
  "SNTI": {
    "Settlement Date": "Nov 15, 2024",
    "Short Interest": 57980,
    "Avg. Daily Volume": 22480,
    "Short Float": "2.01%",
    "Short Ratio": "2.58"
  },
  "RGTI": {
    "Settlement Date": "Nov 15, 2024",
    "Short Interest": 26130000,
    "Avg. Daily Volume": 5910000,
    "Short Float": "16.49%",
    "Short Ratio": "4.42"
  },
  "KDLY": {
    "Settlement Date": "Nov 15, 2024",
    "Short Interest": 80100,
    "Avg. Daily Volume": 246080,
    "Short Float": "4.22%",
    "Short Ratio": "0.33"
  },
  "PPBT": {
    "Settlement Date": "Nov 15, 2024",
    "Short Interest": 34620,
    "Avg. Daily Volume": 39140,
    "Short Float": "1.92%",
    "Short Ratio": "0.88"
  },
  "UPC": {
    "Settlement Date": "Nov 15, 2024",
    "Short Interest": 2480,
    "Avg. Daily Volume": 223490,
    "Short Float": "0.17%",
    "Short Ratio": "0.01"
  },
  "SHIM": {
    "Settlement Date": "Nov 15, 2024",
    "Short Interest": 65239.99999999999,
    "Avg. Daily Volume": 37790,
    "Short Float": "2.31%",
    "Short Ratio": "1.73"
  },
  "CTOR": {
    "Settlement Date": "Nov 15, 2024",
    "Short Interest": 29770,
    "Avg. Daily Volume": 158890,
    "Short Float": "8.50%",
    "Short Ratio": "0.19"
  },
  "CTNT": {
    "Settlement Date": "Nov 15, 2024",
    "Short Interest": 78150,
    "Avg. Daily Volume": 189290,
    "Short Float": "4.88%",
    "Short Ratio": "0.41"
  },
  "PL": {
    "Settlement Date": "Nov 15, 2024",
    "Short Interest": 6030000,
    "Avg. Daily Volume": 2640000,
    "Short Float": "3.08%",
    "Short Ratio": "2.29"
  },
  "CHRS": {
    "Settlement Date": "Nov 15, 2024",
    "Short Interest": 33040000,
    "Avg. Daily Volume": 2560000,
    "Short Float": "29.88%",
    "Short Ratio": "12.90"
  },
  "PRZO": {
    "Settlement Date": "Nov 15, 2024",
    "Short Interest": 106610,
    "Avg. Daily Volume": 316170,
    "Short Float": "1.18%",
    "Short Ratio": "0.34"
  },
  "BCLI": {
    "Settlement Date": "Nov 15, 2024",
    "Short Interest": 173850,
    "Avg. Daily Volume": 69420,
    "Short Float": "3.56%",
    "Short Ratio": "2.50"
  },
  "JFBR": {
    "Settlement Date": "Nov 15, 2024",
    "Short Interest": 26510,
    "Avg. Daily Volume": 195700,
    "Short Float": "0.40%",
    "Short Ratio": "0.14"
  },
  "ZENA": {
    "Settlement Date": "Nov 15, 2024",
    "Short Interest": 290670,
    "Avg. Daily Volume": 3460000,
    "Short Float": "15.09%",
    "Short Ratio": "0.08"
  },
  "PSQH": {
    "Settlement Date": "Nov 15, 2024",
    "Short Interest": 1250000,
    "Avg. Daily Volume": 148780,
    "Short Float": "7.58%",
    "Short Ratio": "8.42"
  },
  "CETX": {
    "Settlement Date": "Nov 15, 2024",
    "Short Interest": 4440,
    "Avg. Daily Volume": 149920,
    "Short Float": "0.61%",
    "Short Ratio": "0.03"
  },
  "PBM": {
    "Settlement Date": "Nov 15, 2024",
    "Short Interest": 10980,
    "Avg. Daily Volume": 85120,
    "Short Float": "1.75%",
    "Short Ratio": "0.13"
  },
  "NLSP": {
    "Settlement Date": "Nov 15, 2024",
    "Short Interest": 55990,
    "Avg. Daily Volume": 206840,
    "Short Float": "3.43%",
    "Short Ratio": "0.27"
  },
  "VLN": {
    "Settlement Date": "Nov 15, 2024",
    "Short Interest": 209800,
    "Avg. Daily Volume": 161960,
    "Short Float": "0.26%",
    "Short Ratio": "1.30"
  },
  "TZUP": {
    "Settlement Date": "Nov 15, 2024",
    "Short Interest": 36580,
    "Avg. Daily Volume": 42330,
    "Short Float": "2.14%",
    "Short Ratio": "0.86"
  },
  "ZJK": {
    "Settlement Date": "Nov 15, 2024",
    "Short Interest": 14620,
    "Avg. Daily Volume": 135180,
    "Short Float": "N/A",
    "Short Ratio": "0.11"
  },
  "EOSE": {
    "Settlement Date": "Nov 15, 2024",
    "Short Interest": 57330000,
    "Avg. Daily Volume": 7330000,
    "Short Float": "27.10%",
    "Short Ratio": "7.82"
  },
  "CHR": {
    "Settlement Date": "Nov 15, 2024",
    "Short Interest": 23980,
    "Avg. Daily Volume": 9820,
    "Short Float": "0.43%",
    "Short Ratio": "2.44"
  },
  "VUZI": {
    "Settlement Date": "Nov 15, 2024",
    "Short Interest": 10680000,
    "Avg. Daily Volume": 1080000,
    "Short Float": "17.55%",
    "Short Ratio": "9.88"
  },
  "BTCT": {
    "Settlement Date": "Nov 15, 2024",
    "Short Interest": 1120000,
    "Avg. Daily Volume": 3160000,
    "Short Float": "44.80%",
    "Short Ratio": "0.35"
  },
  "GNLN": {
    "Settlement Date": "Nov 15, 2024",
    "Short Interest": 34490,
    "Avg. Daily Volume": 1340000,
    "Short Float": "2.59%",
    "Short Ratio": "0.03"
  },
  "PRCH": {
    "Settlement Date": "Nov 15, 2024",
    "Short Interest": 8289999.999999999,
    "Avg. Daily Volume": 1660000,
    "Short Float": "13.95%",
    "Short Ratio": "5.00"
  },
  "MUX": {
    "Settlement Date": "Nov 15, 2024",
    "Short Interest": 1070000,
    "Avg. Daily Volume": 627690,
    "Short Float": "2.42%",
    "Short Ratio": "1.71"
  },
  "ENLV": {
    "Settlement Date": "Nov 15, 2024",
    "Short Interest": 99230,
    "Avg. Daily Volume": 125250,
    "Short Float": "0.53%",
    "Short Ratio": "0.79"
  },
  "GPRK": {
    "Settlement Date": "Nov 15, 2024",
    "Short Interest": 969790,
    "Avg. Daily Volume": 321790,
    "Short Float": "2.59%",
    "Short Ratio": "3.01"
  },
  "TRNR": {
    "Settlement Date": "Nov 15, 2024",
    "Short Interest": 76510,
    "Avg. Daily Volume": 138070,
    "Short Float": "191.27%",
    "Short Ratio": "0.55"
  },
  "NVTS": {
    "Settlement Date": "Nov 15, 2024",
    "Short Interest": 27840000,
    "Avg. Daily Volume": 2700000,
    "Short Float": "24.31%",
    "Short Ratio": "10.32"
  }
}