{
  "DRUG": {
    "ticker": "DRUG",
    "news": [],
    "hod": false,
    "float": "2.88M",
    "price": "3.25",
    "time": "00:35:00",
    "isActive": true,
    "firstSeen": "2024-10-15T07:31:32.452Z",
    "lastSeen": "2024-10-15T08:18:31.423Z",
    "shorts": {}
  },
  "RANI": {
    "ticker": "RANI",
    "news": [
      {
        "author": "Benzinga Insights",
        "content": "",
        "created_at": "2024-10-14T16:30:53Z",
        "headline": "12 Health Care Stocks Moving In Monday's Intraday Session",
        "id": 41317394,
        "images": [
          {
            "size": "large",
            "url": "https://cdn.benzinga.com/files/imagecache/2048x1536xUP/images/story/2023/movers_image_18.jpeg"
          },
          {
            "size": "small",
            "url": "https://cdn.benzinga.com/files/imagecache/1024x768xUP/images/story/2023/movers_image_18.jpeg"
          },
          {
            "size": "thumb",
            "url": "https://cdn.benzinga.com/files/imagecache/250x187xUP/images/story/2023/movers_image_18.jpeg"
          }
        ],
        "source": "benzinga",
        "summary": " ",
        "symbols": [
          "GRTS",
          "IBO",
          "INVO",
          "IVA",
          "LBPH",
          "MTEM",
          "MYNZ",
          "NUWE",
          "RANI",
          "TRIB",
          "TVGN",
          "VRPX"
        ],
        "updated_at": "2024-10-14T16:30:53Z",
        "url": "https://www.benzinga.com/insights/movers/24/10/41317394/12-health-care-stocks-moving-in-mondays-intraday-session"
      },
      {
        "author": "Avi Kapoor",
        "content": "",
        "created_at": "2024-10-14T11:04:30Z",
        "headline": "Why Longboard Pharmaceuticals Shares Are Trading Higher By Around 47%; Here Are 20 Stocks Moving Premarket",
        "id": 41310058,
        "images": [
          {
            "size": "large",
            "url": "https://cdn.benzinga.com/files/imagecache/2048x1536xUP/images/story/2024/10/14/movers-image_11.jpeg"
          },
          {
            "size": "small",
            "url": "https://cdn.benzinga.com/files/imagecache/1024x768xUP/images/story/2024/10/14/movers-image_11.jpeg"
          },
          {
            "size": "thumb",
            "url": "https://cdn.benzinga.com/files/imagecache/250x187xUP/images/story/2024/10/14/movers-image_11.jpeg"
          }
        ],
        "source": "benzinga",
        "summary": " ",
        "symbols": [
          "ARBK",
          "BLND",
          "BYU",
          "CERS",
          "DXYZ",
          "IBG",
          "IVA",
          "LBPH",
          "MTEM",
          "NIVF",
          "NTBL",
          "PACB",
          "RANI",
          "RILY",
          "SPPL",
          "TVGN",
          "TWG",
          "VEV",
          "XPON",
          "ZPTA"
        ],
        "updated_at": "2024-10-14T14:49:13Z",
        "url": "https://www.benzinga.com/news/24/10/41310058/why-longboard-pharmaceuticals-shares-are-trading-higher-by-around-47-here-are-20-stocks-moving-prema"
      },
      {
        "author": "Benzinga Insights",
        "content": "",
        "created_at": "2024-10-14T12:08:59Z",
        "headline": "12 Health Care Stocks Moving In Monday's Pre-Market Session",
        "id": 41311032,
        "images": [
          {
            "size": "large",
            "url": "https://cdn.benzinga.com/files/imagecache/2048x1536xUP/images/story/2023/movers_image_0.jpeg"
          },
          {
            "size": "small",
            "url": "https://cdn.benzinga.com/files/imagecache/1024x768xUP/images/story/2023/movers_image_0.jpeg"
          },
          {
            "size": "thumb",
            "url": "https://cdn.benzinga.com/files/imagecache/250x187xUP/images/story/2023/movers_image_0.jpeg"
          }
        ],
        "source": "benzinga",
        "summary": " ",
        "symbols": [
          "DWTX",
          "GRI",
          "HSTM",
          "IMRN",
          "IVA",
          "JSPR",
          "LBPH",
          "MTEM",
          "NIVF",
          "RANI",
          "TVGN",
          "VRPX"
        ],
        "updated_at": "2024-10-14T12:08:59Z",
        "url": "https://www.benzinga.com/insights/movers/24/10/41311032/12-health-care-stocks-moving-in-mondays-pre-market-session"
      }
    ],
    "hod": false,
    "float": "27.34M",
    "price": "3.88",
    "time": "23:38:33",
    "isActive": true,
    "firstSeen": "2024-10-15T07:31:32.460Z",
    "lastSeen": "2024-10-15T08:23:03.067Z",
    "shorts": {
      "Settlement Date": "Sep 30, 2024",
      "Short Interest": 788590,
      "Avg. Daily Volume": 55060,
      "Short Float": "5.26%",
      "Short Ratio": "14.32"
    }
  },
  "OKLO": {
    "ticker": "OKLO",
    "news": [
      {
        "author": "Adam Eckert",
        "content": "",
        "created_at": "2024-10-14T21:21:52Z",
        "headline": "Sam Altman's Oklo Jumps On Google Nuclear Deal: What's Going On?",
        "id": 41321236,
        "images": [
          {
            "size": "large",
            "url": "https://cdn.benzinga.com/files/imagecache/2048x1536xUP/images/story/2024/10/14/Oklo-Powerhouse-3-Datacenter.jpeg"
          },
          {
            "size": "small",
            "url": "https://cdn.benzinga.com/files/imagecache/1024x768xUP/images/story/2024/10/14/Oklo-Powerhouse-3-Datacenter.jpeg"
          },
          {
            "size": "thumb",
            "url": "https://cdn.benzinga.com/files/imagecache/250x187xUP/images/story/2024/10/14/Oklo-Powerhouse-3-Datacenter.jpeg"
          }
        ],
        "source": "benzinga",
        "summary": "Oklo Inc (NYSE:OKLO) shares popped in afternoon trading Monday after Alphabet Inc (NASDAQ:GOOG) announced intentions to purchase power from small modular reactor (SMR) developer Kairos Power.",
        "symbols": [
          "GOOG",
          "GOOGL",
          "OKLO"
        ],
        "updated_at": "2024-10-14T21:21:53Z",
        "url": "https://www.benzinga.com/news/24/10/41321236/sam-altmans-oklo-jumps-on-google-nuclear-deal-whats-going-on"
      }
    ],
    "hod": true,
    "float": "69.46M",
    "price": "11.38",
    "time": "23:35:38",
    "isActive": true,
    "firstSeen": "2024-10-15T07:31:32.463Z",
    "lastSeen": "2024-10-15T07:31:32.463Z",
    "shorts": {
      "Settlement Date": "Sep 30, 2024",
      "Short Interest": 8580000,
      "Avg. Daily Volume": 3060000,
      "Short Float": "12.35%",
      "Short Ratio": "2.81"
    }
  },
  "BNZI": {
    "ticker": "BNZI",
    "news": [
      {
        "author": "Benzinga Insights",
        "content": "",
        "created_at": "2024-10-14T16:30:43Z",
        "headline": "12 Information Technology Stocks Moving In Monday's Intraday Session",
        "id": 41317391,
        "images": [
          {
            "size": "large",
            "url": "https://cdn.benzinga.com/files/imagecache/2048x1536xUP/images/story/2023/movers_image_5.jpeg"
          },
          {
            "size": "small",
            "url": "https://cdn.benzinga.com/files/imagecache/1024x768xUP/images/story/2023/movers_image_5.jpeg"
          },
          {
            "size": "thumb",
            "url": "https://cdn.benzinga.com/files/imagecache/250x187xUP/images/story/2023/movers_image_5.jpeg"
          }
        ],
        "source": "benzinga",
        "summary": " ",
        "symbols": [
          "ALAR",
          "BNZI",
          "HOLO",
          "KC",
          "OCFT",
          "OST",
          "SELX",
          "UBXG",
          "VERB",
          "WTO",
          "XTIA",
          "ZPTA"
        ],
        "updated_at": "2024-10-14T16:30:43Z",
        "url": "https://www.benzinga.com/insights/movers/24/10/41317391/12-information-technology-stocks-moving-in-mondays-intraday-session"
      },
      {
        "author": "Benzinga Insights",
        "content": "",
        "created_at": "2024-10-14T12:08:43Z",
        "headline": "12 Information Technology Stocks Moving In Monday's Pre-Market Session",
        "id": 41311028,
        "images": [
          {
            "size": "large",
            "url": "https://cdn.benzinga.com/files/imagecache/2048x1536xUP/images/story/2023/movers_image_0.jpeg"
          },
          {
            "size": "small",
            "url": "https://cdn.benzinga.com/files/imagecache/1024x768xUP/images/story/2023/movers_image_0.jpeg"
          },
          {
            "size": "thumb",
            "url": "https://cdn.benzinga.com/files/imagecache/250x187xUP/images/story/2023/movers_image_0.jpeg"
          }
        ],
        "source": "benzinga",
        "summary": " ",
        "symbols": [
          "ALAR",
          "AUUD",
          "BLND",
          "BNZI",
          "BTCT",
          "SGN",
          "VERB",
          "VUZI",
          "WRAP",
          "XTKG",
          "ZENA",
          "ZPTA"
        ],
        "updated_at": "2024-10-14T12:08:44Z",
        "url": "https://www.benzinga.com/insights/movers/24/10/41311028/12-information-technology-stocks-moving-in-mondays-pre-market-session"
      }
    ],
    "hod": false,
    "float": "3.06M",
    "price": "5.6",
    "time": "10:43:01",
    "isActive": true,
    "firstSeen": "2024-10-15T08:42:27.925Z",
    "lastSeen": "2024-10-15T08:42:27.925Z",
    "shorts": {
      "Settlement Date": "Sep 30, 2024",
      "Short Interest": 127140,
      "Avg. Daily Volume": 2080000,
      "Short Float": "16.95%",
      "Short Ratio": "0.06"
    }
  }
}